tkone/__init__.py
tkone/_custom.py
tkone/_custom.pyi
tkone/_tkinter.py
TkOne-0.0.1.dist-info/LICENSE
TkOne-0.0.1.dist-info/METADATA
TkOne-0.0.1.dist-info/WHEEL
TkOne-0.0.1.dist-info/top_level.txt
TkOne-0.0.1.dist-info/RECORD
